dj_tenants/__init__.py
dj_tenants/apps.py
dj_tenants/conf.py
dj_tenants/context.py
dj_tenants/exceptions.py
dj_tenants/middleware.py
dj_tenants/models.py
dj_tenants/postgres_backend/__init__.py
dj_tenants/postgres_backend/base.py
dj_tenants/postgres_backend/compiler.py
dj_tenants/postgres_backend/operations.py
dj_tenants/utils.py
dj_tenants-0.1.4.dist-info/METADATA
dj_tenants-0.1.4.dist-info/WHEEL
dj_tenants-0.1.4.dist-info/RECORD
