Metadata-Version: 2.1
Name: dj-tenants
Version: 0.1.4
Summary: 
Author: Hugo Mesquita
Author-email: hugohomesquita@gmail.com
Requires-Python: >=3.12,<4.0
Classifier: Programming Language :: Python :: 3
Classifier: Programming Language :: Python :: 3.12
Requires-Dist: django (>=5.0.4,<6.0.0)
Requires-Dist: django-appconf (>=1.0.4,<2.0.0)
